README.md
setup.py
gaussian_fermions/hopping_Hamiltonian.py
gaussian_fermions/tunneling_covariance_matrix.py
gaussian_fermions.egg-info/PKG-INFO
gaussian_fermions.egg-info/SOURCES.txt
gaussian_fermions.egg-info/dependency_links.txt
gaussian_fermions.egg-info/not-zip-safe
gaussian_fermions.egg-info/top_level.txt