Metadata-Version: 1.0
Name: gaussian-fermions
Version: 0.1
Summary: A set of functions useful for calculations of properties of fermions in a Gaussian regime.
Home-page: https://github.com/marekgluza/Gaussian_fermions.git
Author: Marek Gluza
Author-email: gluza@zedat.fu-berlin.de
License: GPL-3.0
Platform: UNKNOWN
